cricapi/Cricapi.py
cricapi/__init__.py
cricapi-1.1.dist-info/LICENSE
cricapi-1.1.dist-info/METADATA
cricapi-1.1.dist-info/WHEEL
cricapi-1.1.dist-info/top_level.txt
cricapi-1.1.dist-info/RECORD
