Metadata-Version: 2.1
Name: cricapi
Version: 1.1
Summary: The cricapi, Free to use, super-high bandwidth, high performance Cricket API. Targeted at Developers and Cricket lovers.
Home-page: https://github.com/KarthikGangadhar/pycricapi
Author: kgangadhar
Author-email: karthikg1643@gmail.com
License: UNKNOWN
Download-URL: https://github.com/KarthikGangadhar/pycricapi/tarball/1.0
Keywords: cricket,matchSchedule,playerstat,crciketScore,matches,fantasysquard,fantasysummary,playerfinder
Platform: UNKNOWN
Classifier: Development Status :: 5 - Production/Stable
Classifier: Intended Audience :: Developers
Classifier: Natural Language :: English
Classifier: License :: OSI Approved :: Apache Software License
Classifier: Programming Language :: Python
Classifier: Programming Language :: Python :: 2
Classifier: Programming Language :: Python :: 2.7
Classifier: Programming Language :: Python :: 3
Classifier: Programming Language :: Python :: 3.4
Classifier: Programming Language :: Python :: 3.5
Classifier: Programming Language :: Python :: 3.6
Classifier: Programming Language :: Python :: 3.7
Classifier: Programming Language :: Python :: Implementation :: CPython
Classifier: Programming Language :: Python :: Implementation :: PyPy
